UselessMath/UselessMath.py
UselessMath/__init__.py
uselessmath-0.0.4.dist-info/licenses/LICENSE
uselessmath-0.0.4.dist-info/METADATA
uselessmath-0.0.4.dist-info/WHEEL
uselessmath-0.0.4.dist-info/top_level.txt
uselessmath-0.0.4.dist-info/RECORD
