Metadata-Version: 2.4
Name: UselessMath
Version: 0.0.4
Summary: A python library to do the most basic, useless math
Home-page: https://github.com/Ricca665/UselessMath
Author: Ricca665
License: MIT
Classifier: Programming Language :: Python :: 3
Classifier: License :: OSI Approved :: MIT License
Classifier: Operating System :: OS Independent
Requires-Python: >=3.11
License-File: LICENSE
Dynamic: author
Dynamic: classifier
Dynamic: description
Dynamic: description-content-type
Dynamic: home-page
Dynamic: license
Dynamic: license-file
Dynamic: requires-python
Dynamic: summary
